pytelco/__init__.py
pytelco/features/__init__.py
pytelco/features/cdr.py
pytelco/features/gtpu.py
pytelco/features/sip.py
pytelco/io/__init__.py
pytelco/io/loaders.py
pytelco/preprocessing/__init__.py
pytelco/preprocessing/cleaning.py
pytelco/preprocessing/feature_utils.py
pytelco/preprocessing/time_series.py
pytelco/preprocessing/validation.py
pytelco/temporal/__init__.py
pytelco/temporal/lags.py
pytelco/temporal/sequences.py
pytelco/temporal/trends.py
pytelco-0.2.2.dist-info/licenses/LICENSE
pytelco-0.2.2.dist-info/METADATA
pytelco-0.2.2.dist-info/WHEEL
pytelco-0.2.2.dist-info/top_level.txt
pytelco-0.2.2.dist-info/RECORD
