Metadata-Version: 2.4
Name: pytelco
Version: 0.2.2
Summary: The Telco Data Science Toolkit - sklearn-style library for telecommunications data analysis
Author: PyTelco Contributors
License: MIT
Project-URL: Homepage, https://github.com/girishgouda16/PyTelco
Project-URL: Documentation, https://github.com/girishgouda16/PyTelco#readme
Project-URL: Repository, https://github.com/girishgouda16/PyTelco
Project-URL: Issues, https://github.com/girishgouda16/PyTelco/issues
Keywords: telecommunications,data-science,machine-learning,feature-engineering,time-series,CDR,SIP,GTP-U,churn-prediction,network-analytics
Classifier: Development Status :: 4 - Beta
Classifier: Intended Audience :: Developers
Classifier: Intended Audience :: Science/Research
Classifier: License :: OSI Approved :: MIT License
Classifier: Operating System :: OS Independent
Classifier: Programming Language :: Python :: 3
Classifier: Programming Language :: Python :: 3.8
Classifier: Programming Language :: Python :: 3.9
Classifier: Programming Language :: Python :: 3.10
Classifier: Programming Language :: Python :: 3.11
Classifier: Programming Language :: Python :: 3.12
Classifier: Topic :: Scientific/Engineering
Classifier: Topic :: Scientific/Engineering :: Artificial Intelligence
Requires-Python: >=3.8
License-File: LICENSE
Requires-Dist: pandas>=1.3.0
Requires-Dist: numpy>=1.20.0
Requires-Dist: scipy>=1.7.0
Requires-Dist: scikit-learn>=1.0.0
Provides-Extra: dev
Requires-Dist: pytest>=7.0.0; extra == "dev"
Requires-Dist: pytest-cov>=4.0.0; extra == "dev"
Requires-Dist: black>=23.0.0; extra == "dev"
Requires-Dist: isort>=5.0.0; extra == "dev"
Requires-Dist: mypy>=1.0.0; extra == "dev"
Dynamic: license-file
